mkdocs_recently_updated_docs/__init__.py
mkdocs_recently_updated_docs/plugin.py
mkdocs_recently_updated_docs/templates/recently_updated_group.html
mkdocs_recently_updated_docs-1.4.dist-info/licenses/LICENSE
mkdocs_recently_updated_docs-1.4.dist-info/METADATA
mkdocs_recently_updated_docs-1.4.dist-info/WHEEL
mkdocs_recently_updated_docs-1.4.dist-info/entry_points.txt
mkdocs_recently_updated_docs-1.4.dist-info/top_level.txt
mkdocs_recently_updated_docs-1.4.dist-info/RECORD
