Metadata-Version: 2.4
Name: mkdocs-recently-updated-docs
Version: 1.4
Summary: A MkDocs plugin to show recently updated documents
Author-email: Aaron Wang <aaronwqt@gmail.com>
License: MIT
Project-URL: Homepage, https://github.com/jaywhj/mkdocs-recently-updated-docs
Project-URL: Documentation, https://jaywhj.netlify.app/document-dates-en
Classifier: Programming Language :: Python :: 3
Classifier: Operating System :: OS Independent
Requires-Python: >=3.7
License-File: LICENSE
Requires-Dist: mkdocs>=1.1.0
Requires-Dist: mkdocs-document-dates>=3.5
Dynamic: license-file
